pyecodevices/__init__.py
pyecodevices-1.7.0.dist-info/LICENSE
pyecodevices-1.7.0.dist-info/METADATA
pyecodevices-1.7.0.dist-info/WHEEL
pyecodevices-1.7.0.dist-info/top_level.txt
pyecodevices-1.7.0.dist-info/RECORD
