Metadata-Version: 2.1
Name: pyecodevices
Version: 1.7.0
Summary: Get information from GCE Eco-Devices.
Home-page: https://github.com/aohzan/pyecodevices
Author: Aohzan
Author-email: aohzan@gmail.com
Classifier: Programming Language :: Python :: 3
Classifier: License :: OSI Approved :: MIT License
Classifier: Operating System :: OS Independent
Requires-Python: >=3.8
License-File: LICENSE
